__init__.py
linux_do_oauth.py
new_api_linux_do_oauth_token-0.0.0.dist-info/METADATA
new_api_linux_do_oauth_token-0.0.0.dist-info/WHEEL
new_api_linux_do_oauth_token-0.0.0.dist-info/licenses/LICENSE
new_api_linux_do_oauth_token-0.0.0.dist-info/RECORD
