Metadata-Version: 2.4
Name: new-api-linux-do-oauth-token
Version: 0.0.0
Summary: A helper library to authenticate new-api with linux.do oauth and retrieve session
License: MIT
License-File: LICENSE
Author: Sn0wo2
Requires-Python: >=3.12
Classifier: License :: OSI Approved :: MIT License
Classifier: Programming Language :: Python :: 3
Classifier: Programming Language :: Python :: 3.12
Classifier: Programming Language :: Python :: 3.13
Classifier: Programming Language :: Python :: 3.14
Requires-Dist: linux-do-connect-token (==0.0.3)
